colorfield/__init__.py
colorfield/apps.py
colorfield/fields.py
colorfield/static/colorfield/jscolor.js
colorfield/static/colorfield/jscolor.min.js
colorfield/templates/colorfield/color.html
colorfield/templates/colorfield/color.html~
django_postgresql_rgb_colorfield-1.1.0.dist-info/METADATA
django_postgresql_rgb_colorfield-1.1.0.dist-info/RECORD
django_postgresql_rgb_colorfield-1.1.0.dist-info/WHEEL
django_postgresql_rgb_colorfield-1.1.0.dist-info/top_level.txt
