Metadata-Version: 2.1
Name: django-postgresql-rgb-colorfield
Version: 1.1.0
Summary: A ColorField to save Colors in RGB array in postgresql.
Home-page: https://gitlab.com/codesigntheory/django-postgresql-rgb-colorfield
Author: Utsob Roy
Author-email: roy@codesign.com.bd
License: Mozilla Public License 2.0 (MPL 2.0)
Platform: UNKNOWN
Classifier: Environment :: Web Environment
Classifier: Framework :: Django
Classifier: Framework :: Django :: 2.0
Classifier: Intended Audience :: Developers
Classifier: License :: OSI Approved :: Mozilla Public License 2.0 (MPL 2.0)
Classifier: Operating System :: OS Independent
Classifier: Programming Language :: Python
Classifier: Programming Language :: Python :: 3.5
Classifier: Programming Language :: Python :: 3.6
Classifier: Topic :: Internet :: WWW/HTTP
Classifier: Topic :: Internet :: WWW/HTTP :: Dynamic Content
Requires-Dist: webcolors
